odoo/addons/purchase_order_qty_change_no_recompute/README.rst
odoo/addons/purchase_order_qty_change_no_recompute/__init__.py
odoo/addons/purchase_order_qty_change_no_recompute/__manifest__.py
odoo/addons/purchase_order_qty_change_no_recompute/monkeypatching.py
odoo/addons/purchase_order_qty_change_no_recompute/i18n/es.po
odoo/addons/purchase_order_qty_change_no_recompute/i18n/it.po
odoo/addons/purchase_order_qty_change_no_recompute/i18n/purchase_order_qty_change_no_recompute.pot
odoo/addons/purchase_order_qty_change_no_recompute/readme/CONTRIBUTORS.md
odoo/addons/purchase_order_qty_change_no_recompute/readme/DESCRIPTION.md
odoo/addons/purchase_order_qty_change_no_recompute/readme/USAGE.md
odoo/addons/purchase_order_qty_change_no_recompute/static/description/icon.png
odoo/addons/purchase_order_qty_change_no_recompute/static/description/index.html
odoo/addons/purchase_order_qty_change_no_recompute/tests/__init__.py
odoo/addons/purchase_order_qty_change_no_recompute/tests/test_purchase_order_qty_change.py
odoo_addon_purchase_order_qty_change_no_recompute-18.0.1.0.0.2.dist-info/METADATA
odoo_addon_purchase_order_qty_change_no_recompute-18.0.1.0.0.2.dist-info/WHEEL
odoo_addon_purchase_order_qty_change_no_recompute-18.0.1.0.0.2.dist-info/top_level.txt
odoo_addon_purchase_order_qty_change_no_recompute-18.0.1.0.0.2.dist-info/RECORD
